equacao_segundo_grau/__init__.py
equacao_segundo_grau/baskara.py
equacao_segundo_grau-0.0.1.dist-info/METADATA
equacao_segundo_grau-0.0.1.dist-info/WHEEL
equacao_segundo_grau-0.0.1.dist-info/top_level.txt
equacao_segundo_grau-0.0.1.dist-info/RECORD
