Metadata-Version: 2.1
Name: equacao-segundo-grau
Version: 0.0.1
Summary: Calcula o resultado para equações do segundo grau
Home-page: https://github.com/GenildoPraca/equacao-segundo-grau-package.git
Author: Genildo
Author-email: genildo.praca@gmail.com
License: UNKNOWN
Platform: UNKNOWN
Requires-Python: >=3.8
